{
	"planets": [
		{
			"x": 0.5,
			"y": 0.1,
			"growth": 2,
			"ships": 100
		},
		{
			"x": 0.25,
			"y": 0.25,
			"growth": 1,
			"ships": 100
		},
		{
			"x": 0.75,
			"y": 0.25,
			"growth": 1,
			"ships": 100
		},
		{
			"x": 0.5,
			"y": 0.4,
			"growth": 1,
			"ships": 100
		},
		{
			"x": 0.5,
			"y": 0.6,
			"growth": 1,
			"ships": 100
		},
		{
			"x": 0.5,
			"y": 0.9,
			"growth": 2,
			"ships": 100
		},
		{
			"x": 0.25,
			"y": 0.75,
			"growth": 1,
			"ships": 100
		},
		{
			"x": 0.75,
			"y": 0.75,
			"growth": 1,
			"ships": 100
		}
	]
}